Metadata-Version: 2.1
Name: pykickloc
Version: 1.0.0
Summary: pykickloc is a python implementation of the KickLoc localization algorithm.
Home-page: https://github.com/LumineerLabs/pykicklock
Author: Lane Haury
Author-email: lane@lumineerlabs.com
License: UNKNOWN
Platform: UNKNOWN
Classifier: License :: OSI Approved :: MIT License
Classifier: Programming Language :: Python
Classifier: Operating System :: OS Independent
